diagnosis_viewer/__init__.py
diagnosis_viewer/extension.py
localstack_extension_diagnosis_viewer-0.1.1.dist-info/METADATA
localstack_extension_diagnosis_viewer-0.1.1.dist-info/WHEEL
localstack_extension_diagnosis_viewer-0.1.1.dist-info/entry_points.txt
localstack_extension_diagnosis_viewer-0.1.1.dist-info/top_level.txt
localstack_extension_diagnosis_viewer-0.1.1.dist-info/RECORD
