Metadata-Version: 2.1
Name: localstack-extension-diagnosis-viewer
Version: 0.1.1
Summary: LocalStack Extension: Diagnosis Viewer
Home-page: https://github.com/localstack/localstack-extensions/tree/main/diagnosis-viewer
Author: LocalStack Contributors
Author-email: info@localstack.cloud
Requires-Dist: diapretty
Provides-Extra: dev
Requires-Dist: localstack-core >=1.4 ; extra == 'dev'
